cryptonet
