Metadata-Version: 1.0
Name: Cryptonet
Version: 0.0.5
Summary: Blockchain and Cryptonet Framework
Home-page: UNKNOWN
Author: Max Kaye
Author-email: max@eudemonia.io
License: UNKNOWN
Platform: UNKNOWN
